app/__init__.py
app/main.py
app/core/__init__.py
app/core/auth.py
app/core/imports.py
app/core/manifest.py
app/core/prompts_provider.py
app/core/registry.py
app/core/settings.py
app/core/templates.py
app/services/__init__.py
app/services/constants.py
app/services/search_assets/__init__.py
app/services/search_assets/models/__init__.py
app/services/search_assets/models/search_asset.py
app/services/search_assets/tools/__init__.py
app/services/search_assets/tools/search_asset.py
app/shared/__init__.py
app/shared/exceptions/__init__.py
app/shared/exceptions/base.py
app/shared/logging/__init__.py
app/shared/logging/constants.py
app/shared/logging/filter.py
app/shared/logging/generate_context.py
app/shared/logging/utils.py
app/shared/models/__init__.py
app/shared/models/ssl_config.py
app/shared/utils/__init__.py
app/shared/utils/helpers.py
app/shared/utils/http_client.py
app/shared/utils/ssl_utils.py
rsamal_mcp_server-0.0.1.dist-info/METADATA
rsamal_mcp_server-0.0.1.dist-info/WHEEL
rsamal_mcp_server-0.0.1.dist-info/entry_points.txt
rsamal_mcp_server-0.0.1.dist-info/top_level.txt
rsamal_mcp_server-0.0.1.dist-info/RECORD
